{
  "subtree": [
    {
      "speaker": "Oracle",
      "line": "I know who the would-be murderer is."
    },
    {
      "speaker": "King Nico",
      "line": "Who is it?!"
    },
    {
      "speaker": "Oracle",
      "line": "Your uncle, sire. He is in league with the local thieves guild and intends to put himself on the throne."
    },
    {
      "speaker": "King Nico",
      "line": "The scoundrel! If he thinks he can kill his own kin, he will have to learn a lesson."
    },
    {
      "speaker": "King Nico",
      "line": "Thank you for all that you've done. The royal guard will take it from here."
    }
  ]
}
